pysfer/__init__.py
pysfer/guarded_file.py
pysfer/pysfer.py
pysfer-0.3.dist-info/LICENSE
pysfer-0.3.dist-info/METADATA
pysfer-0.3.dist-info/WHEEL
pysfer-0.3.dist-info/top_level.txt
pysfer-0.3.dist-info/RECORD
