Metadata-Version: 2.1
Name: pysfer
Version: 0.3
Summary: Pysfer is a Python library for transfering data between python procseses.
Home-page: https://github.com/metaphaz/pysfer
Author: Yiğit Özan
Author-email: yigit.muhittin.57@gmail.com
Classifier: Programming Language :: Python :: 3
Classifier: License :: OSI Approved :: MIT License
Classifier: Operating System :: OS Independent
Requires-Python: >=3.7
License-File: LICENSE
